sfirat_haomer/__init__.py
sfirat_haomer/core.py
sfirat_haomer/data.py
sfirat_haomer-1.0.0.dist-info/licenses/LICENSE
sfirat_haomer-1.0.0.dist-info/METADATA
sfirat_haomer-1.0.0.dist-info/WHEEL
sfirat_haomer-1.0.0.dist-info/top_level.txt
sfirat_haomer-1.0.0.dist-info/RECORD
