Metadata-Version: 2.4
Name: sfirat-haomer
Version: 1.0.0
Summary: Get Sefirat HaOmer count and text by Hebrew or Gregorian date
Author-email: Your Name <your.email@example.com>
License: MIT
License-File: LICENSE
Requires-Dist: convertdate
Dynamic: license-file
